[
  {
    "name": "Unishirt",
    "imageURL": "https://www.google.com/url?sa=i&url=https%3A%2F%2Fid.hm.com%2Fid_id%2Fshirt-jacket-0902864003010.html&psig=AOvVaw3QPZjJ2NY_MpZGq8uoWGGM&ust=1650590657065000&source=images&cd=vfe&ved=0CAwQjRxqFwoTCKDNpsD_o_cCFQAAAAAdAAAAABAE",
    "description": "Shirt jacket in woven fabric with a collar and press-studs down the front. Long sleeves with a slit and buttoned cuffs, flap chest pockets with a button, an inner pocket and a straight-cut hem. Lined.",
    "price": 50000,
    "CategoryId": 1,
    "UserId": 1,
    "isBuy": true
  }
]